{
  "Author": "FyteClub Team",
  "Name": "FyteClub",
  "InternalName": "FyteClub",
  "AssemblyVersion": "1.0.0.0",
  "Description": "[SOURCE DISTRIBUTION] Automatically share and synchronize character mods with nearby players. Requires local compilation with Dalamud SDK.",
  "ApplicableVersion": "any",
  "RepoUrl": "https://github.com/fyteclubplugin/fyteclub",
  "Tags": [
    "mods",
    "sharing",
    "character",
    "customization"
  ],
  "DalamudApiLevel": 13,
  "LoadRequiredState": 0,
  "LoadSync": false,
  "CanUnloadAsync": false,
  "LoadPriority": 0,
  "ImageUrls": [],
  "IconUrl": "",
  "Punchline": "You do not talk about FyteClub",
  "AcceptsFeedback": true
}